AUTHORS
LICENSE
MANIFEST.in
README
setup.py
ahc/__init__.py
ahc/ahc.py
ahc.egg-info/PKG-INFO
ahc.egg-info/SOURCES.txt
ahc.egg-info/dependency_links.txt
ahc.egg-info/entry_points.txt
ahc.egg-info/namespace_packages.txt
ahc.egg-info/not-zip-safe
ahc.egg-info/requires.txt
ahc.egg-info/top_level.txt
ahc/libraries/__init__.py
ahc/libraries/apache.py
ahc/libraries/configs.py
ahc/libraries/core_http.py
ahc/libraries/core_http_tests.py
ahc/libraries/encfs.py
ahc/libraries/fs.py
ahc/libraries/helpers.py
ahc/libraries/password.py
ahc/libraries/path.py
ahc/modules/__init__.py
ahc/modules/apache.py
ahc/modules/backup.py
ahc/modules/bind.py
ahc/modules/certs.py
ahc/modules/crypt.py
ahc/modules/ftp.py
ahc/modules/git.py
ahc/modules/git_jail.py
ahc/modules/install.py
ahc/modules/mysql.py
ahc/modules/nginx.py
ahc/modules/shop.py
ahc/modules/test.py
ahc/modules/vbox.py
ahc/modules/vpn.py
ahc/modules/web.py
ahc/templates/.DS_Store
ahc/templates/apache2-auth.conf
ahc/templates/apache2-confluence.conf
ahc/templates/apache2-django-mod_python-venv.conf
ahc/templates/apache2-django-wsgi.conf
ahc/templates/apache2-django.conf
ahc/templates/apache2-jira.conf
ahc/templates/apache2-php.conf
ahc/templates/apache2-php.php
ahc/templates/apache2-python-mod_python-venv.conf
ahc/templates/apache2-python-mod_python-venv.py
ahc/templates/apache2-python-wsgi.conf
ahc/templates/apache2-python-wsgi.py
ahc/templates/apache2-python.conf
ahc/templates/apache2-python.py
ahc/templates/apache2-ror.conf
ahc/templates/apache2-ruby.conf
ahc/templates/apache2-ruby.rb
ahc/templates/apache2-ssl-cert.conf
ahc/templates/apache2-static-tune.conf
ahc/templates/bashrc.conf
ahc/templates/bind9-zone.conf
ahc/templates/bind9.conf
ahc/templates/dropbox-runner.conf
ahc/templates/fw.conf
ahc/templates/git-jail-gitignore-default.conf
ahc/templates/git-jail-post-commit-repo.conf
ahc/templates/git-jail-post-receive-real-repo.conf
ahc/templates/git-jail-post-receive-repo.conf
ahc/templates/git-jail-post-receive-user-repo.conf
ahc/templates/git-jail.sh
ahc/templates/git-post-receive.conf
ahc/templates/git-shell-enforce-directory.py
ahc/templates/gitconfig
ahc/templates/lamp.sh
ahc/templates/lighttpd-vhost.conf
ahc/templates/lighttpd.conf
