Metadata-Version: 1.1
Name: ahc
Version: 1.5.0
Summary: Package with extensions for Developers on Python(+Django), Ruby(+RoR) and PHP.
Home-page: http://github.com/gotlium/ahc
Author: GoTLiuM InSPiRiT
Author-email: gotlium@gmail.com
License: GPL-2
Keywords: console utils developers
Platform: UNKNOWN
Classifier: Environment :: Console
Classifier: Development Status :: 5 - Production/Stable
Classifier: Intended Audience :: Developers
Classifier: License :: OSI Approved :: GNU General Public License (GPL)
Classifier: Natural Language :: English
Classifier: Operating System :: POSIX :: Linux
Classifier: Programming Language :: Python :: 2.7
Classifier: Topic :: Utilities
